{"_id":{"$oid":"6122f226a1f290c8be2ba28e"},"Username":"lainamae","Password":"test123","Email":"lainamae@gmail.com","Birthday":{"$date":"1995-05-01T00:00:00Z"},"FavoriteMovies":[{"$oid":"6122f226a1f290c8be2ba28e"},{"$oid":"6122f229a1f290c8be2ba28f"},{"$oid":"6122f22ca1f290c8be2ba290"}]}
{"_id":{"$oid":"6122f229a1f290c8be2ba28f"},"Username":"oliviajoon","Password":"password456","Email":"oliviajoon@gmail.com","Birthday":{"$date":"1995-06-19T00:00:00Z"},"FavoriteMovies":[{"$oid":"6122e5bba1f290c8be2ba287"},{"$oid":"6122e65aa1f290c8be2ba288"},{"$oid":"6122e7c2a1f290c8be2ba28a"}]}
{"_id":{"$oid":"6122f22ca1f290c8be2ba290"},"Username":"lupusrex","Password":"text789","Email":"lexieruben@gmail.com","Birthday":{"$date":"1995-10-19T00:00:00Z"},"FavoriteMovies":[{"$oid":"6122e91ca1f290c8be2ba28c"},{"$oid":"6122e42fa1f290c8be2ba285"},{"$oid":"6122e521a1f290c8be2ba286"}]}
{"_id":{"$oid":"6126c540a1f290c8be2ba292"},"Username":"margo25","Password":"password2021","Email":"margobirdie@gmail.com","Birthday":{"$date":"2001-04-20T00:00:00Z"},"FavoriteMovies":[{"$oid":"6122e91ca1f290c8be2ba28c"},{"$oid":"6122e7c2a1f290c8be2ba28a"},{"$oid":"6122e65aa1f290c8be2ba288"}]}
